{
  "entry": "server.js",
  "files": {
    "pages/admin/news/_id/index.js": "pages/admin/news/_id/index.js",
    "pages/admin/news/create.js": "pages/admin/news/create.js",
    "pages/admin/news/index.js": "pages/admin/news/index.js",
    "pages/admin/place/_id/index.js": "pages/admin/place/_id/index.js",
    "pages/admin/place/create.js": "pages/admin/place/create.js",
    "pages/admin/place/index.js": "pages/admin/place/index.js",
    "pages/admin/placeGroup/_id/index.js": "pages/admin/placeGroup/_id/index.js",
    "pages/admin/placeGroup/create.js": "pages/admin/placeGroup/create.js",
    "pages/admin/placeGroup/index.js": "pages/admin/placeGroup/index.js",
    "pages/admin/reserve/_id/index.js": "pages/admin/reserve/_id/index.js",
    "pages/admin/reserve/create.js": "pages/admin/reserve/create.js",
    "pages/admin/reserve/index.js": "pages/admin/reserve/index.js",
    "pages/admin/zone/_id/index.js": "pages/admin/zone/_id/index.js",
    "pages/admin/zone/create.js": "pages/admin/zone/create.js",
    "pages/admin/zone/index.js": "pages/admin/zone/index.js",
    "pages/coffee/_id/index.js": "pages/coffee/_id/index.js",
    "pages/food/_id/index.js": "pages/food/_id/index.js",
    "pages/hotel/_id/index.js": "pages/hotel/_id/index.js",
    "pages/index.js": "pages/index.js",
    "pages/login/index.js": "pages/login/index.js",
    "pages/map/_id/index.js": "pages/map/_id/index.js",
    "pages/news/_id/index.js": "pages/news/_id/index.js",
    "pages/news/index.js": "pages/news/index.js",
    "pages/place/_id/index.js": "pages/place/_id/index.js",
    "pages/reserve/index.js": "pages/reserve/index.js",
    "pages/travel/_id/index.js": "pages/travel/_id/index.js",
    "server.js": "server.js"
  },
  "maps": {
    "pages/admin/news/_id/index.js": "pages/admin/news/_id/index.js.map",
    "pages/admin/news/create.js": "pages/admin/news/create.js.map",
    "pages/admin/news/index.js": "pages/admin/news/index.js.map",
    "pages/admin/place/_id/index.js": "pages/admin/place/_id/index.js.map",
    "pages/admin/place/create.js": "pages/admin/place/create.js.map",
    "pages/admin/place/index.js": "pages/admin/place/index.js.map",
    "pages/admin/placeGroup/_id/index.js": "pages/admin/placeGroup/_id/index.js.map",
    "pages/admin/placeGroup/create.js": "pages/admin/placeGroup/create.js.map",
    "pages/admin/placeGroup/index.js": "pages/admin/placeGroup/index.js.map",
    "pages/admin/reserve/_id/index.js": "pages/admin/reserve/_id/index.js.map",
    "pages/admin/reserve/create.js": "pages/admin/reserve/create.js.map",
    "pages/admin/reserve/index.js": "pages/admin/reserve/index.js.map",
    "pages/admin/zone/_id/index.js": "pages/admin/zone/_id/index.js.map",
    "pages/admin/zone/create.js": "pages/admin/zone/create.js.map",
    "pages/admin/zone/index.js": "pages/admin/zone/index.js.map",
    "pages/coffee/_id/index.js": "pages/coffee/_id/index.js.map",
    "pages/food/_id/index.js": "pages/food/_id/index.js.map",
    "pages/hotel/_id/index.js": "pages/hotel/_id/index.js.map",
    "pages/index.js": "pages/index.js.map",
    "pages/login/index.js": "pages/login/index.js.map",
    "pages/map/_id/index.js": "pages/map/_id/index.js.map",
    "pages/news/_id/index.js": "pages/news/_id/index.js.map",
    "pages/news/index.js": "pages/news/index.js.map",
    "pages/place/_id/index.js": "pages/place/_id/index.js.map",
    "pages/reserve/index.js": "pages/reserve/index.js.map",
    "pages/travel/_id/index.js": "pages/travel/_id/index.js.map",
    "server.js": "server.js.map"
  }
}